setup.py
sanutils/__init__.py
sanutils.egg-info/PKG-INFO
sanutils.egg-info/SOURCES.txt
sanutils.egg-info/dependency_links.txt
sanutils.egg-info/not-zip-safe
sanutils.egg-info/top_level.txt