Metadata-Version: 1.0
Name: sanutils
Version: 0.1
Summary: Utilities Toolbox for Sanjeev and By Sanjeev
Home-page: https://github.com/sanjeevshrestha/sanutils
Author: Sanjeev Shrestha
Author-email: UNKNOWN
License: MIT
Platform: UNKNOWN
